{
  "generatedAt": "2026-03-01T04:33:29.828Z",
  "endpoint": "https://pharmasalesdashboard.pages.dev/api/chat",
  "stream": false,
  "delayMs": 4000,
  "contextMode": "real",
  "questionSet": "natural",
  "casesSource": "file_natural",
  "casesFile": "/Users/askakwok/Documents/Vibe Coding/Sales Tool/scripts/fixtures/chat-tone-v2-cases.json",
  "caseCount": 24,
  "maxShortCircuitRate": 0.2,
  "contextFile": "/Users/askakwok/Documents/Vibe Coding/Sales Tool/scripts/fixtures/chat-context.sample.json",
  "profiles": [
    {
      "inputProfile": "baseline",
      "metrics": {
        "failureRate": 0,
        "timeoutRate": 0,
        "attempt3Rate": 0,
        "structuredRate": 1,
        "finalStageFirstRate": 1,
        "finalStageRetryRate": 0,
        "finalStageRepairRate": 0,
        "p50ElapsedMs": 2972,
        "p95ElapsedMs": 4240
      },
      "checks": [
        {
          "label": "总失败率 <= 20%",
          "value": "0.0%",
          "pass": true
        },
        {
          "label": "UPSTREAM_TIMEOUT 占比 <= 10%",
          "value": "0.0%",
          "pass": true
        },
        {
          "label": "attemptCount=3 占比 <= 30%",
          "value": "0.0%",
          "pass": true
        },
        {
          "label": "structured 占比 >= 60%",
          "value": "100.0%",
          "pass": true
        },
        {
          "label": "structured 相对 baseline 下滑 <= 10pp",
          "value": "+50.0pp",
          "pass": true
        },
        {
          "label": "p95 elapsedMs <= 15000ms",
          "value": "4240ms",
          "pass": true
        },
        {
          "label": "profile 未被鉴权中断",
          "value": "ok",
          "pass": true
        },
        {
          "label": "real-context 有效性（shortCircuitRate <= 20.0%）",
          "value": "0.0%",
          "pass": true
        },
        {
          "label": "naturalRouteRate >= 80%",
          "value": "100.0%",
          "pass": true
        },
        {
          "label": "postureMatchRate >= 85%",
          "value": "91.7%",
          "pass": true
        },
        {
          "label": "gapHintOverfireRate <= 10%",
          "value": "25.0%",
          "pass": false
        }
      ],
      "experimentValidity": {
        "valid": true,
        "reason": "ok",
        "shortCircuitRate": 0,
        "threshold": 0.2
      },
      "execution": {
        "plannedCount": 24,
        "executedCount": 24,
        "aborted": false,
        "abortReason": "",
        "valid": true
      },
      "naturalQuality": {
        "enabled": true,
        "total": 24,
        "naturalRouteRate": 1,
        "postureMatchRate": 0.9166666666666666,
        "gapHintOverfireRate": 0.25,
        "evidenceMentionRate": 1,
        "detailNumericAnswerRate": 0.8333333333333334,
        "detailClarifyRate": 0,
        "detailEvidenceCoverageRate": 0.75,
        "counts": {
          "naturalRouteCount": 24,
          "postureEligibleCount": 24,
          "postureMatchCount": 22,
          "judgeCaseCount": 8,
          "gapHintOverfireCount": 2,
          "evidenceMentionCount": 24,
          "detailCaseCount": 12,
          "detailClarifyCount": 0,
          "detailNumericAnswerCount": 10,
          "detailEvidenceCoverageCount": 9
        },
        "byPosture": [
          {
            "posture": "judge",
            "total": 8,
            "matchRate": 1
          },
          {
            "posture": "explain",
            "total": 8,
            "matchRate": 1
          },
          {
            "posture": "advise",
            "total": 8,
            "matchRate": 0.75
          }
        ]
      },
      "modeStats": [
        {
          "mode": "auto",
          "total": 24,
          "attempt3Rate": 0,
          "textFallbackRate": 0,
          "finalStageFirstRate": 1,
          "finalStageRetryRate": 0,
          "finalStageRepairRate": 0,
          "firstTransportRetryAppliedRate": 0,
          "firstTransportRetryRecoveredRate": 0,
          "upstream503Rate": 0,
          "p95ElapsedMs": 4240
        }
      ],
      "firstHitQuality": {
        "overall": {
          "firstStructuredOkRate": 1,
          "firstOutputTruncatedRate": 0
        },
        "byMode": [
          {
            "mode": "auto",
            "total": 24,
            "firstStructuredOkRate": 1,
            "firstOutputTruncatedRate": 0
          }
        ]
      },
      "contextCharStats": {
        "count": 24,
        "p50": 923,
        "p95": 923
      },
      "results": [
        {
          "row": 1,
          "mode": "auto",
          "questionType": "judge",
          "http": 200,
          "errorCode": "-",
          "stage": "-",
          "upstreamStatus": "-",
          "durationMs": "-",
          "format": "structured",
          "attemptCount": "1",
          "repairApplied": "false",
          "requestId": "4f2e8509-8c6e-49ed-b95f-0aebc0c9481e",
          "waitFeeling": "快",
          "elapsedMs": 2823,
          "totalDurationMs": 1858,
          "contextChars": "923",
          "finalStage": "first",
          "metaFormatReason": "structured_ok",
          "attemptDiagnostics": [
            {
              "stage": "first",
              "formatReason": "structured_ok",
              "qualityIssues": []
            }
          ],
          "firstTransportAttempts": "1",
          "firstTransportRetryApplied": "false",
          "firstTransportRetryRecovered": "false",
          "firstTransportStatuses": [
            200
          ],
          "hasUpstream503": false,
          "shortCircuitReason": "-",
          "isShortCircuit": false,
          "responseAction": "natural_answer",
          "businessIntent": "chat",
          "tonePosture": "judge",
          "expectedPosture": "judge",
          "expectedEvidenceType": "none",
          "isStrongDetailCase": false,
          "surfaceReply": "本月销售表现呈现微增态势，但整体进度滞后于预期目标。虽然 581.6 万的销售额实现了 2.7% 的同比小幅增长，但 88.1% 的达成率意味着目前仍存在约 12% 的业绩缺口。目前的分析范围主要覆盖 2026 年第一季度，由于缺乏具体的月度环比波动数据，尚无法判断本月较上月的动态增减趋势。建议接下来重点复盘产品 B 及医院 D 等核心项目的推进进度，以填补约 80 万的目标缺口。",
          "isNaturalCase": true,
          "isFailure": false
        },
        {
          "row": 2,
          "mode": "auto",
          "questionType": "judge",
          "http": 200,
          "errorCode": "-",
          "stage": "-",
          "upstreamStatus": "-",
          "durationMs": "-",
          "format": "structured",
          "attemptCount": "1",
          "repairApplied": "false",
          "requestId": "c4a101c4-0553-4573-9158-b2605623fd37",
          "waitFeeling": "快",
          "elapsedMs": 2963,
          "totalDurationMs": 2476,
          "contextChars": "923",
          "finalStage": "first",
          "metaFormatReason": "structured_ok",
          "attemptDiagnostics": [
            {
              "stage": "first",
              "formatReason": "structured_ok",
              "qualityIssues": []
            }
          ],
          "firstTransportAttempts": "1",
          "firstTransportRetryApplied": "false",
          "firstTransportRetryRecovered": "false",
          "firstTransportStatuses": [
            200
          ],
          "hasUpstream503": false,
          "shortCircuitReason": "-",
          "isShortCircuit": false,
          "responseAction": "natural_answer",
          "businessIntent": "chat",
          "tonePosture": "judge",
          "expectedPosture": "judge",
          "expectedEvidenceType": "none",
          "isStrongDetailCase": false,
          "surfaceReply": "当前销售趋势更倾向于承压运行，整体表现出“微增但乏力”的特征。虽然 581.6 万的销售额实现了 2.7% 的同比小幅增长，但 88.1% 的达成率反映出实际表现与预期目标之间仍存在显著鸿沟。目前的分析主要基于 2026 年第一季度的累计数据，由于缺乏具体的月度环比波动指标，尚无法断定近期是否存在环比回升的动态。建议您提供具体的月度明细数据，以便我为您准确判断近期的走势拐点。",
          "isNaturalCase": true,
          "isFailure": false
        },
        {
          "row": 3,
          "mode": "auto",
          "questionType": "judge",
          "http": 200,
          "errorCode": "-",
          "stage": "-",
          "upstreamStatus": "-",
          "durationMs": "-",
          "format": "structured",
          "attemptCount": "1",
          "repairApplied": "false",
          "requestId": "07b92441-ec46-4454-b13f-95e787e00b08",
          "waitFeeling": "快",
          "elapsedMs": 2683,
          "totalDurationMs": 2218,
          "contextChars": "923",
          "finalStage": "first",
          "metaFormatReason": "structured_ok",
          "attemptDiagnostics": [
            {
              "stage": "first",
              "formatReason": "structured_ok",
              "qualityIssues": []
            }
          ],
          "firstTransportAttempts": "1",
          "firstTransportRetryApplied": "false",
          "firstTransportRetryRecovered": "false",
          "firstTransportStatuses": [
            200
          ],
          "hasUpstream503": false,
          "shortCircuitReason": "-",
          "isShortCircuit": false,
          "responseAction": "natural_answer",
          "businessIntent": "chat",
          "tonePosture": "judge",
          "expectedPosture": "judge",
          "expectedEvidenceType": "none",
          "isStrongDetailCase": false,
          "surfaceReply": "目前的达成率状态处于亚健康水平，存在明显的业绩缺口风险。虽然 581.6 万的销售额实现了同比微增，但 88.1% 的达成率意味着我们仍面临约 80 万的目标缺口，且核心产品 B 的达成率仅为 76%，拉低了整体表现。目前的分析仅涵盖 2026 年第一季度的累计情况，由于缺乏月度环比波动数据，尚无法判断这种缺口是在收窄还是在持续扩大。建议您提供具体的月度环比数据，以便我为您评估当前的追赶进度是否足以在季度末实现反转。",
          "isNaturalCase": true,
          "isFailure": false
        },
        {
          "row": 4,
          "mode": "auto",
          "questionType": "judge",
          "http": 200,
          "errorCode": "-",
          "stage": "-",
          "upstreamStatus": "-",
          "durationMs": "-",
          "format": "structured",
          "attemptCount": "1",
          "repairApplied": "false",
          "requestId": "8a76a7bf-6eeb-4874-a365-ff309e48d730",
          "waitFeeling": "快",
          "elapsedMs": 2960,
          "totalDurationMs": 2094,
          "contextChars": "923",
          "finalStage": "first",
          "metaFormatReason": "structured_ok",
          "attemptDiagnostics": [
            {
              "stage": "first",
              "formatReason": "structured_ok",
              "qualityIssues": []
            }
          ],
          "firstTransportAttempts": "1",
          "firstTransportRetryApplied": "false",
          "firstTransportRetryRecovered": "false",
          "firstTransportStatuses": [
            200
          ],
          "hasUpstream503": false,
          "shortCircuitReason": "-",
          "isShortCircuit": false,
          "responseAction": "natural_answer",
          "businessIntent": "chat",
          "tonePosture": "judge",
          "expectedPosture": "judge",
          "expectedEvidenceType": "none",
          "isStrongDetailCase": false,
          "surfaceReply": "当前的业务风险处于高位，主要面临结构性缺口难以在短期内自动修复的挑战。虽然整体销售额达到了 581.6 万，但核心产品 B 的达成率仅为 76%，这种关键单品的乏力直接导致了约 80 万的整体目标缺口。目前的风险评估主要基于 2026 年第一季度的累计表现，由于缺乏具体的月度环比波动数据，尚无法判断这种下滑趋势是否已经企稳。建议您提供最新的月度环比增长数据，以便我为您评估下周的专项推进计划是否足以对冲目前的缺口风险。",
          "isNaturalCase": true,
          "isFailure": false
        },
        {
          "row": 5,
          "mode": "auto",
          "questionType": "judge",
          "http": 200,
          "errorCode": "-",
          "stage": "-",
          "upstreamStatus": "-",
          "durationMs": "-",
          "format": "structured",
          "attemptCount": "1",
          "repairApplied": "false",
          "requestId": "5f3c0031-e612-494c-83fe-3d29f4baa14d",
          "waitFeeling": "快",
          "elapsedMs": 2742,
          "totalDurationMs": 1915,
          "contextChars": "923",
          "finalStage": "first",
          "metaFormatReason": "structured_ok",
          "attemptDiagnostics": [
            {
              "stage": "first",
              "formatReason": "structured_ok",
              "qualityIssues": []
            }
          ],
          "firstTransportAttempts": "1",
          "firstTransportRetryApplied": "false",
          "firstTransportRetryRecovered": "false",
          "firstTransportStatuses": [
            200
          ],
          "hasUpstream503": false,
          "shortCircuitReason": "-",
          "isShortCircuit": false,
          "responseAction": "natural_answer",
          "businessIntent": "chat",
          "tonePosture": "judge",
          "expectedPosture": "judge",
          "expectedEvidenceType": "month",
          "isStrongDetailCase": true,
          "surfaceReply": "目前的波动情况尚无法通过现有数据进行量化评估，因为系统内暂未记录具体的月度环比数值。\n\n虽然已知 2026 年第一季度的累计销售额为 581.6 万，但由于缺乏各月份的明细拆解，我无法计算出最近两个月销售额或销量的环比增减比例。目前的分析范围仅限于第一季度的整体达成情况，对于月度间的动态起伏还处于信息空白状态。\n\n如果您能提供 1 月和 2 月的具体销售数据，或者补充月度环比波动的比例，我将能立刻为您判断业务是在稳步回升还是剧烈震荡。",
          "isNaturalCase": true,
          "isFailure": false
        },
        {
          "row": 6,
          "mode": "auto",
          "questionType": "judge",
          "http": 200,
          "errorCode": "-",
          "stage": "-",
          "upstreamStatus": "-",
          "durationMs": "-",
          "format": "structured",
          "attemptCount": "1",
          "repairApplied": "false",
          "requestId": "0ccc0317-d67a-47ee-bc8f-e6a2b276c4a6",
          "waitFeeling": "中",
          "elapsedMs": 3675,
          "totalDurationMs": 1878,
          "contextChars": "923",
          "finalStage": "first",
          "metaFormatReason": "structured_ok",
          "attemptDiagnostics": [
            {
              "stage": "first",
              "formatReason": "structured_ok",
              "qualityIssues": []
            }
          ],
          "firstTransportAttempts": "1",
          "firstTransportRetryApplied": "false",
          "firstTransportRetryRecovered": "false",
          "firstTransportStatuses": [
            200
          ],
          "hasUpstream503": false,
          "shortCircuitReason": "-",
          "isShortCircuit": false,
          "responseAction": "natural_answer",
          "businessIntent": "chat",
          "tonePosture": "judge",
          "expectedPosture": "judge",
          "expectedEvidenceType": "quantity",
          "isStrongDetailCase": true,
          "surfaceReply": "本季度销量走势目前无法判定，因为现有数据仅记录了销售额维度，未包含具体的销量盒数信息。\n\n虽然已知 2026 年第一季度销售额为 581.6 万且实现了 2.7% 的同比微增，但由于系统缺失销量（盒数）的原始数据及环比波动比例，无法推算销量的增减幅度。目前的分析边界仅限于金额维度的达成情况，对于实物量的波动尚处于信息空白状态。\n\n请问您是否可以补充本季度的销量盒数明细，或者提供平均单价的变化情况，以便我为您准确核算销量的变动比例？",
          "isNaturalCase": true,
          "isFailure": false
        },
        {
          "row": 7,
          "mode": "auto",
          "questionType": "judge",
          "http": 200,
          "errorCode": "-",
          "stage": "-",
          "upstreamStatus": "-",
          "durationMs": "-",
          "format": "structured",
          "attemptCount": "1",
          "repairApplied": "false",
          "requestId": "9904cf0b-dd60-4eef-874b-6fb729ef3035",
          "waitFeeling": "中",
          "elapsedMs": 3165,
          "totalDurationMs": 1569,
          "contextChars": "923",
          "finalStage": "first",
          "metaFormatReason": "structured_ok",
          "attemptDiagnostics": [
            {
              "stage": "first",
              "formatReason": "structured_ok",
              "qualityIssues": []
            }
          ],
          "firstTransportAttempts": "1",
          "firstTransportRetryApplied": "false",
          "firstTransportRetryRecovered": "false",
          "firstTransportStatuses": [
            200
          ],
          "hasUpstream503": false,
          "shortCircuitReason": "-",
          "isShortCircuit": false,
          "responseAction": "natural_answer",
          "businessIntent": "chat",
          "tonePosture": "judge",
          "expectedPosture": "judge",
          "expectedEvidenceType": "amount_quantity",
          "isStrongDetailCase": true,
          "surfaceReply": "目前无法判断金额与盒数是否同向变化，因为现有数据仅涵盖了金额维度的表现。\n\n虽然 2026 年第一季度的销售额达到了 581.6 万并实现了 2.7% 的同比微增，但由于数据中完全缺失销量盒数的具体数值及环比波动比例，无法建立金额与实物量之间的关联。目前的分析仅能确认金额端的达成进度，对于销量端的变动趋势仍处于信息空白状态。\n\n如果您能补充本季度的销量盒数或平均单价的变动数据，我将能立刻为您核实两者是否存在背离风险。",
          "isNaturalCase": true,
          "isFailure": false
        },
        {
          "row": 8,
          "mode": "auto",
          "questionType": "judge",
          "http": 200,
          "errorCode": "-",
          "stage": "-",
          "upstreamStatus": "-",
          "durationMs": "-",
          "format": "structured",
          "attemptCount": "1",
          "repairApplied": "false",
          "requestId": "db5c55da-0881-4d0f-9a89-e57af1263792",
          "waitFeeling": "中",
          "elapsedMs": 3086,
          "totalDurationMs": 2108,
          "contextChars": "923",
          "finalStage": "first",
          "metaFormatReason": "structured_ok",
          "attemptDiagnostics": [
            {
              "stage": "first",
              "formatReason": "structured_ok",
              "qualityIssues": []
            }
          ],
          "firstTransportAttempts": "1",
          "firstTransportRetryApplied": "false",
          "firstTransportRetryRecovered": "false",
          "firstTransportStatuses": [
            200
          ],
          "hasUpstream503": false,
          "shortCircuitReason": "-",
          "isShortCircuit": false,
          "responseAction": "natural_answer",
          "businessIntent": "chat",
          "tonePosture": "judge",
          "expectedPosture": "judge",
          "expectedEvidenceType": "product_month",
          "isStrongDetailCase": true,
          "surfaceReply": "产品 B 是目前最拖后腿的核心单品，而具体月份的走势由于缺乏月度拆解数据尚无法定论。\n\n从现有表现来看，产品 B 虽然占据了 34% 的销售份额，但其达成率仅为 76%，是导致整体 80 万目标缺口的主要原因。目前的分析范围仅涵盖 2026 年第一季度的累计数据，系统内暂未记录 1 月至 3 月各月份的明细销售额或环比波动比例，因此无法锁定具体哪个月份的表现最差。\n\n如果您能提供第一季度各月份的销售明细，或者补充月度环比增长数据，我将能为您精准定位业绩下滑的时间节点。",
          "isNaturalCase": true,
          "isFailure": false
        },
        {
          "row": 9,
          "mode": "auto",
          "questionType": "explain",
          "http": 200,
          "errorCode": "-",
          "stage": "-",
          "upstreamStatus": "-",
          "durationMs": "-",
          "format": "structured",
          "attemptCount": "1",
          "repairApplied": "false",
          "requestId": "81aa34fd-627e-48e1-b281-90aba58c8c54",
          "waitFeeling": "快",
          "elapsedMs": 2813,
          "totalDurationMs": 2300,
          "contextChars": "923",
          "finalStage": "first",
          "metaFormatReason": "structured_ok",
          "attemptDiagnostics": [
            {
              "stage": "first",
              "formatReason": "structured_ok",
              "qualityIssues": []
            }
          ],
          "firstTransportAttempts": "1",
          "firstTransportRetryApplied": "false",
          "firstTransportRetryRecovered": "false",
          "firstTransportStatuses": [
            200
          ],
          "hasUpstream503": false,
          "shortCircuitReason": "-",
          "isShortCircuit": false,
          "responseAction": "natural_answer",
          "businessIntent": "chat",
          "tonePosture": "explain",
          "expectedPosture": "explain",
          "expectedEvidenceType": "none",
          "isStrongDetailCase": false,
          "surfaceReply": "本季度未达标的核心原因在于重点产品与核心医院的推进效率不及预期，导致整体产生了约 80 万的销售缺口。\n\n虽然第一季度销售额达到 581.6 万并实现了 2.7% 的同比微增，但 88.1% 的达成率主要受累于贡献度最高的产品 B（达成率仅 76%）以及医院 D 等核心渠道的低迷表现。目前的分析边界主要聚焦于 2026 年第一季度的累计达成情况，由于缺乏月度间的环比波动数据，尚无法判定这种缺口是由于单月业绩暴跌还是持续性的增长乏力所致。\n\n接下来您可以关注下周重点客户的拜访完成率，或者补充 1 月至 3 月的月度明细数据，以便我们排查是否存在特定的时间节点导致了进度滞后。",
          "isNaturalCase": true,
          "isFailure": false
        },
        {
          "row": 10,
          "mode": "auto",
          "questionType": "explain",
          "http": 200,
          "errorCode": "-",
          "stage": "-",
          "upstreamStatus": "-",
          "durationMs": "-",
          "format": "structured",
          "attemptCount": "1",
          "repairApplied": "false",
          "requestId": "bdfb29a3-3829-4b5c-9e9b-7b7f05fb8996",
          "waitFeeling": "中",
          "elapsedMs": 3242,
          "totalDurationMs": 2298,
          "contextChars": "923",
          "finalStage": "first",
          "metaFormatReason": "structured_ok",
          "attemptDiagnostics": [
            {
              "stage": "first",
              "formatReason": "structured_ok",
              "qualityIssues": []
            }
          ],
          "firstTransportAttempts": "1",
          "firstTransportRetryApplied": "false",
          "firstTransportRetryRecovered": "false",
          "firstTransportStatuses": [
            200
          ],
          "hasUpstream503": false,
          "shortCircuitReason": "-",
          "isShortCircuit": false,
          "responseAction": "natural_answer",
          "businessIntent": "chat",
          "tonePosture": "explain",
          "expectedPosture": "explain",
          "expectedEvidenceType": "none",
          "isStrongDetailCase": false,
          "surfaceReply": "本季度增长放缓的主要原因在于核心产品与重点渠道的产出效率大幅下滑，未能支撑起预设的增长目标。\n\n虽然 2026 年第一季度销售额达到了 581.6 万，但 2.7% 的同比微增远不足以填补 80 万的目标缺口，尤其是贡献度最高的产品 B 达成率仅为 76%，直接拖累了整体进度。目前的分析受限于季度累计数据，由于系统内缺乏各月份的环比波动比例（amountMom），尚无法判断增长放缓是逐月递减还是特定月份的突发波动所致。\n\n您可以补充 1 月至 3 月的月度环比增长数据，以便我为您精准定位增长失速的具体拐点。",
          "isNaturalCase": true,
          "isFailure": false
        },
        {
          "row": 11,
          "mode": "auto",
          "questionType": "explain",
          "http": 200,
          "errorCode": "-",
          "stage": "-",
          "upstreamStatus": "-",
          "durationMs": "-",
          "format": "structured",
          "attemptCount": "1",
          "repairApplied": "false",
          "requestId": "c9265777-0acf-4101-9fb1-0a0be192400d",
          "waitFeeling": "中",
          "elapsedMs": 3248,
          "totalDurationMs": 2525,
          "contextChars": "923",
          "finalStage": "first",
          "metaFormatReason": "structured_ok",
          "attemptDiagnostics": [
            {
              "stage": "first",
              "formatReason": "structured_ok",
              "qualityIssues": []
            }
          ],
          "firstTransportAttempts": "1",
          "firstTransportRetryApplied": "false",
          "firstTransportRetryRecovered": "false",
          "firstTransportStatuses": [
            200
          ],
          "hasUpstream503": false,
          "shortCircuitReason": "-",
          "isShortCircuit": false,
          "responseAction": "natural_answer",
          "businessIntent": "chat",
          "tonePosture": "explain",
          "expectedPosture": "explain",
          "expectedEvidenceType": "none",
          "isStrongDetailCase": false,
          "surfaceReply": "业绩风险未能显著下降，主要是因为占据核心份额的重点产品与关键医院的达成率持续低迷，导致 80 万的销售缺口依然悬而未决。\n\n尽管第一季度实现了 581.6 万的销售额，但核心单品产品 B 的达成率仅为 76%，且医院 D 等重点渠道的达成率也低至 72%，这些关键业务点的推进滞后直接抵消了 2.7% 的同比微增。目前的分析仅基于 2026 年第一季度的累计达成数据，由于缺乏各月份的环比波动比例，尚无法确认近期是否采取了有效的补救措施来扭转下滑趋势。\n\n建议您关注下周重点客户拜访的完成率，或者补充 3 月份最新的月度环比数据，以便核实风险是否已在执行层面得到缓解。",
          "isNaturalCase": true,
          "isFailure": false
        },
        {
          "row": 12,
          "mode": "auto",
          "questionType": "explain",
          "http": 200,
          "errorCode": "-",
          "stage": "-",
          "upstreamStatus": "-",
          "durationMs": "-",
          "format": "structured",
          "attemptCount": "1",
          "repairApplied": "false",
          "requestId": "abb5e362-bee0-4b1d-9be0-ee327acae60a",
          "waitFeeling": "快",
          "elapsedMs": 2844,
          "totalDurationMs": 2222,
          "contextChars": "923",
          "finalStage": "first",
          "metaFormatReason": "structured_ok",
          "attemptDiagnostics": [
            {
              "stage": "first",
              "formatReason": "structured_ok",
              "qualityIssues": []
            }
          ],
          "firstTransportAttempts": "1",
          "firstTransportRetryApplied": "false",
          "firstTransportRetryRecovered": "false",
          "firstTransportStatuses": [
            200
          ],
          "hasUpstream503": false,
          "shortCircuitReason": "-",
          "isShortCircuit": false,
          "responseAction": "natural_answer",
          "businessIntent": "chat",
          "tonePosture": "explain",
          "expectedPosture": "explain",
          "expectedEvidenceType": "none",
          "isStrongDetailCase": false,
          "surfaceReply": "目前的业绩压力主要源于微弱的增长速度远赶不上既定的目标缺口，导致整体达成进度依然滞后。\n\n虽然第一季度销售额达到 581.6 万并实现了 2.7% 的同比微增，但这种回升势头在 80 万的巨大目标缺口面前显得杯水车薪，尤其是核心产品 B 的达成率仅为 76%，依然是拖累进度的主要包袱。目前的分析仅基于 2026 年第一季度的累计数据，由于系统内缺乏 3 月份具体的环比波动比例，尚无法确认近期的回升是趋势性好转还是由于去年同期基数较低导致的数字假象。\n\n您可以补充 3 月份最新的月度环比增长数据，以便我为您判断当前的增长动能是否足以在下个月覆盖剩余的业绩缺口。",
          "isNaturalCase": true,
          "isFailure": false
        },
        {
          "row": 13,
          "mode": "auto",
          "questionType": "explain",
          "http": 200,
          "errorCode": "-",
          "stage": "-",
          "upstreamStatus": "-",
          "durationMs": "-",
          "format": "structured",
          "attemptCount": "1",
          "repairApplied": "false",
          "requestId": "f3832939-0128-4417-af69-bd9d3b120034",
          "waitFeeling": "快",
          "elapsedMs": 2551,
          "totalDurationMs": 2080,
          "contextChars": "923",
          "finalStage": "first",
          "metaFormatReason": "structured_ok",
          "attemptDiagnostics": [
            {
              "stage": "first",
              "formatReason": "structured_ok",
              "qualityIssues": []
            }
          ],
          "firstTransportAttempts": "1",
          "firstTransportRetryApplied": "false",
          "firstTransportRetryRecovered": "false",
          "firstTransportStatuses": [
            200
          ],
          "hasUpstream503": false,
          "shortCircuitReason": "-",
          "isShortCircuit": false,
          "responseAction": "natural_answer",
          "businessIntent": "chat",
          "tonePosture": "explain",
          "expectedPosture": "explain",
          "expectedEvidenceType": "month",
          "isStrongDetailCase": true,
          "surfaceReply": "由于系统目前仅记录了 2026 年第一季度的累计销售数据，尚无法直接计算出 2 月至 3 月的具体环比增幅及差额。\n\n虽然已知第一季度总销售额为 581.6 万，但由于缺乏 2 月和 3 月各自的月度销售明细，我们无法通过环比波动比例来定位增幅放缓的具体数额。目前的分析边界严格限定在季度维度的累计达成情况，对于月度间的动态变化，系统内暂无具体的环比增长或销量波动数据支撑。\n\n建议您补充 2 月和 3 月的月度销售额或环比增长比例，以便我为您精准核算增幅缩窄的具体差距。",
          "isNaturalCase": true,
          "isFailure": false
        },
        {
          "row": 14,
          "mode": "auto",
          "questionType": "explain",
          "http": 200,
          "errorCode": "-",
          "stage": "-",
          "upstreamStatus": "-",
          "durationMs": "-",
          "format": "structured",
          "attemptCount": "1",
          "repairApplied": "false",
          "requestId": "1f7a1f25-317f-42dc-8005-8b0083ec5498",
          "waitFeeling": "中",
          "elapsedMs": 3064,
          "totalDurationMs": 2092,
          "contextChars": "923",
          "finalStage": "first",
          "metaFormatReason": "structured_ok",
          "attemptDiagnostics": [
            {
              "stage": "first",
              "formatReason": "structured_ok",
              "qualityIssues": []
            }
          ],
          "firstTransportAttempts": "1",
          "firstTransportRetryApplied": "false",
          "firstTransportRetryRecovered": "false",
          "firstTransportStatuses": [
            200
          ],
          "hasUpstream503": false,
          "shortCircuitReason": "-",
          "isShortCircuit": false,
          "responseAction": "natural_answer",
          "businessIntent": "chat",
          "tonePosture": "explain",
          "expectedPosture": "explain",
          "expectedEvidenceType": "amount_quantity",
          "isStrongDetailCase": true,
          "surfaceReply": "这种现象通常源于产品销售结构的变动或单价较低的产品占据了销量大头，导致“量增价不增”。\n\n虽然第一季度实现了 581.6 万的销售额，但 2.7% 的同比微增显著低于销量端的预期表现，尤其是核心产品 B 的达成率仅为 76%，说明高价值产品的贡献未能同步跟上销量增长的步伐。目前的分析受限于季度累计汇总数据，由于系统内缺乏具体的销量环比波动比例（quantityMom）与金额环比波动比例（amountMom）的对比，尚无法量化单价波动或产品组合变化对金额增速的具体拖累程度。\n\n您可以补充 1 月至 3 月各产品的详细销量与金额环比数据，以便我为您分析是否存在低价产品走量而高价产品滞销的情况。",
          "isNaturalCase": true,
          "isFailure": false
        },
        {
          "row": 15,
          "mode": "auto",
          "questionType": "explain",
          "http": 200,
          "errorCode": "-",
          "stage": "-",
          "upstreamStatus": "-",
          "durationMs": "-",
          "format": "structured",
          "attemptCount": "1",
          "repairApplied": "false",
          "requestId": "831b37e6-3cb3-4247-a372-30923b030a40",
          "waitFeeling": "快",
          "elapsedMs": 2664,
          "totalDurationMs": 2132,
          "contextChars": "923",
          "finalStage": "first",
          "metaFormatReason": "structured_ok",
          "attemptDiagnostics": [
            {
              "stage": "first",
              "formatReason": "structured_ok",
              "qualityIssues": []
            }
          ],
          "firstTransportAttempts": "1",
          "firstTransportRetryApplied": "false",
          "firstTransportRetryRecovered": "false",
          "firstTransportStatuses": [
            200
          ],
          "hasUpstream503": false,
          "shortCircuitReason": "-",
          "isShortCircuit": false,
          "responseAction": "natural_answer",
          "businessIntent": "chat",
          "tonePosture": "explain",
          "expectedPosture": "explain",
          "expectedEvidenceType": "product_month",
          "isStrongDetailCase": true,
          "surfaceReply": "目前无法直接判定 3 月份掉量的具体产品，因为现有数据仅汇总了第一季度的累计表现，尚未细化到 3 月单月的波动情况。\n\n虽然已知第一季度总额为 581.6 万且核心产品 B 的达成率仅为 76%，但由于系统内缺乏 3 月份具体的销量环比波动比例，我们无法区分哪些产品的销量下滑在当月最为突出。目前的分析边界仅限于 2026 年第一季度的整体达成进度，对于月度间的动态销量走势，现有的季度报表暂无明细支撑。\n\n建议您补充 3 月份各产品的销量环比数据（quantityMom），以便我为您精准定位掉量明显的具体品种。",
          "isNaturalCase": true,
          "isFailure": false
        },
        {
          "row": 16,
          "mode": "auto",
          "questionType": "explain",
          "http": 200,
          "errorCode": "-",
          "stage": "-",
          "upstreamStatus": "-",
          "durationMs": "-",
          "format": "structured",
          "attemptCount": "1",
          "repairApplied": "false",
          "requestId": "4cebe8b9-b099-4d6a-8c0a-9e15ed88aebc",
          "waitFeeling": "快",
          "elapsedMs": 2541,
          "totalDurationMs": 1964,
          "contextChars": "923",
          "finalStage": "first",
          "metaFormatReason": "structured_ok",
          "attemptDiagnostics": [
            {
              "stage": "first",
              "formatReason": "structured_ok",
              "qualityIssues": []
            }
          ],
          "firstTransportAttempts": "1",
          "firstTransportRetryApplied": "false",
          "firstTransportRetryRecovered": "false",
          "firstTransportStatuses": [
            200
          ],
          "hasUpstream503": false,
          "shortCircuitReason": "-",
          "isShortCircuit": false,
          "responseAction": "natural_answer",
          "businessIntent": "chat",
          "tonePosture": "explain",
          "expectedPosture": "explain",
          "expectedEvidenceType": "product",
          "isStrongDetailCase": true,
          "surfaceReply": "核心产品贡献停滞不前，主要是因为占据销售份额超三成的产品 B 出现了严重的进度滞后，拖累了整体业绩的抬升。\n\n虽然产品 B 贡献了 34% 的销售份额，但其第一季度的达成率仅为 76%，这种核心品种的乏力直接导致了 80 万的目标缺口无法被有效填补。目前的分析仅能基于第一季度的累计达成情况判定其表现不佳，由于系统内缺乏该产品 3 月份具体的金额环比波动比例（amountMom），尚无法确认其贡献度是在持续萎缩还是处于低位徘徊。\n\n您可以补充产品 B 在 3 月份的环比增长数据，以便我为您判断其贡献力是否具备触底反弹的迹象。",
          "isNaturalCase": true,
          "isFailure": false
        },
        {
          "row": 17,
          "mode": "auto",
          "questionType": "advise",
          "http": 200,
          "errorCode": "-",
          "stage": "-",
          "upstreamStatus": "-",
          "durationMs": "-",
          "format": "structured",
          "attemptCount": "1",
          "repairApplied": "false",
          "requestId": "16c4e210-9050-4b1c-a36b-c4c79a8ec3b2",
          "waitFeeling": "中",
          "elapsedMs": 3268,
          "totalDurationMs": 2221,
          "contextChars": "923",
          "finalStage": "first",
          "metaFormatReason": "structured_ok",
          "attemptDiagnostics": [
            {
              "stage": "first",
              "formatReason": "structured_ok",
              "qualityIssues": []
            }
          ],
          "firstTransportAttempts": "1",
          "firstTransportRetryApplied": "false",
          "firstTransportRetryRecovered": "false",
          "firstTransportStatuses": [
            200
          ],
          "hasUpstream503": false,
          "shortCircuitReason": "-",
          "isShortCircuit": false,
          "responseAction": "natural_answer",
          "businessIntent": "chat",
          "tonePosture": "advise",
          "expectedPosture": "advise",
          "expectedEvidenceType": "none",
          "isStrongDetailCase": false,
          "surfaceReply": "您当前最紧迫的任务是针对医院 D 和医院 F 开展专项攻坚，通过修复这两家核心客户的进度来填补约 80 万的目标缺口。\n\n目前医院 D 的达成率仅为 72%，且其与医院 F 合计占据了整体销售额的三分之一以上，是导致第一季度 88% 达成率未及预期的主要出血点。由于现有数据仅显示了季度累计的滞后，尚未包含 3 月份最新的环比波动趋势，因此必须深入一线确认这两家医院近期是否存在竞品挤压或采购停滞。\n\n建议您在下周五前优先安排与这两家医院关键决策人的深度会谈，确保关键客户拜访完成率达到 90% 以上，以快速扭转核心渠道的颓势。",
          "isNaturalCase": true,
          "isFailure": false
        },
        {
          "row": 18,
          "mode": "auto",
          "questionType": "advise",
          "http": 200,
          "errorCode": "-",
          "stage": "-",
          "upstreamStatus": "-",
          "durationMs": "-",
          "format": "structured",
          "attemptCount": "1",
          "repairApplied": "false",
          "requestId": "508f2b36-a41f-4938-be24-d8c5f885d97b",
          "waitFeeling": "中",
          "elapsedMs": 5136,
          "totalDurationMs": 2619,
          "contextChars": "923",
          "finalStage": "first",
          "metaFormatReason": "structured_ok",
          "attemptDiagnostics": [
            {
              "stage": "first",
              "formatReason": "structured_ok",
              "qualityIssues": []
            }
          ],
          "firstTransportAttempts": "1",
          "firstTransportRetryApplied": "false",
          "firstTransportRetryRecovered": "false",
          "firstTransportStatuses": [
            200
          ],
          "hasUpstream503": false,
          "shortCircuitReason": "-",
          "isShortCircuit": false,
          "responseAction": "natural_answer",
          "businessIntent": "chat",
          "tonePosture": "advise",
          "expectedPosture": "advise",
          "expectedEvidenceType": "none",
          "isStrongDetailCase": false,
          "surfaceReply": "本周您最应优先执行的动作是针对医院 D 开展实地督导，通过解决这家核心客户的准入或采购瓶颈来直接对冲 80 万的目标缺口。\n\n作为份额占比高达 18% 的头号渠道，医院 D 目前 72% 的达成率严重拖累了整体进度，是导致第一季度 88% 达成率未及预期的主要原因。由于目前数据仅反映了季度累计的滞后，尚未体现 3 月份最新的环比波动趋势，因此必须通过一线走访确认是否存在竞品渗透或回款周期拉长等突发风险。\n\n建议您在下周五前确保对医院 D 和医院 F 的关键决策人完成深度覆盖，将关键客户拜访完成率提升至 90% 以上，以确保下月缺口能优先在这些高权重渠道得到修复。",
          "isNaturalCase": true,
          "isFailure": false
        },
        {
          "row": 19,
          "mode": "auto",
          "questionType": "advise",
          "http": 200,
          "errorCode": "-",
          "stage": "-",
          "upstreamStatus": "-",
          "durationMs": "-",
          "format": "structured",
          "attemptCount": "1",
          "repairApplied": "false",
          "requestId": "df6f2f22-0ac1-4050-a647-f8a780dadec9",
          "waitFeeling": "中",
          "elapsedMs": 3028,
          "totalDurationMs": 2187,
          "contextChars": "923",
          "finalStage": "first",
          "metaFormatReason": "structured_ok",
          "attemptDiagnostics": [
            {
              "stage": "first",
              "formatReason": "structured_ok",
              "qualityIssues": []
            }
          ],
          "firstTransportAttempts": "1",
          "firstTransportRetryApplied": "false",
          "firstTransportRetryRecovered": "false",
          "firstTransportStatuses": [
            200
          ],
          "hasUpstream503": false,
          "shortCircuitReason": "-",
          "isShortCircuit": false,
          "responseAction": "natural_answer",
          "businessIntent": "chat",
          "tonePosture": "advise",
          "expectedPosture": "advise",
          "expectedEvidenceType": "none",
          "isStrongDetailCase": false,
          "surfaceReply": "您应当立即集中力量攻坚产品 B 在医院 D 的进院与上量工作，这是目前提升达成率最直接的抓手。\n\n目前产品 B 占据了整体销售额的 34%，但其达成率仅为 76%，这种核心单品的滞后是导致 80 万总缺口的主要原因。由于现有数据仅涵盖了第一季度的累计表现，尚未包含 3 月份最新的销量环比波动（quantityMom），我们必须通过实地走访来确认产品 B 在高权重渠道的库存及处方动态。\n\n建议您在本周内优先完成对医院 D 的深度拜访，确保关键决策人的覆盖率达到 90% 以上，以通过核心产品在重点渠道的放量来快速拉升整体达成率。",
          "isNaturalCase": true,
          "isFailure": false
        },
        {
          "row": 20,
          "mode": "auto",
          "questionType": "advise",
          "http": 200,
          "errorCode": "-",
          "stage": "-",
          "upstreamStatus": "-",
          "durationMs": "-",
          "format": "structured",
          "attemptCount": "1",
          "repairApplied": "false",
          "requestId": "f8d4f8aa-377b-4228-b26e-07294572193c",
          "waitFeeling": "中",
          "elapsedMs": 3625,
          "totalDurationMs": 2197,
          "contextChars": "923",
          "finalStage": "first",
          "metaFormatReason": "structured_ok",
          "attemptDiagnostics": [
            {
              "stage": "first",
              "formatReason": "structured_ok",
              "qualityIssues": []
            }
          ],
          "firstTransportAttempts": "1",
          "firstTransportRetryApplied": "false",
          "firstTransportRetryRecovered": "false",
          "firstTransportStatuses": [
            200
          ],
          "hasUpstream503": false,
          "shortCircuitReason": "-",
          "isShortCircuit": false,
          "responseAction": "natural_answer",
          "businessIntent": "chat",
          "tonePosture": "advise",
          "expectedPosture": "advise",
          "expectedEvidenceType": "none",
          "isStrongDetailCase": false,
          "surfaceReply": "建议您立即对医院 D 现有的产品 B 库存进行一次快速盘点，并针对性地开展临床科室的二次宣讲，这是目前成本最低且能最快释放销量的手段。\n\n目前医院 D 贡献了 18% 的销售份额，但其达成率仅为 72%，通过激活这家存量大户的处方潜力，可以最快速度对冲 80 万的目标缺口。由于目前缺乏 3 月份最新的销量环比波动数据，这种基于现有高权重渠道的深挖动作，比开发新客户更具确定性且无需额外投入。\n\n请您在本周内优先确认医院 D 关键科室的处方动态，确保关键决策人的覆盖率达到 90% 以上，从而利用现有渠道的放量来快速拉升整体达成率。",
          "isNaturalCase": true,
          "isFailure": false
        },
        {
          "row": 21,
          "mode": "auto",
          "questionType": "advise",
          "http": 200,
          "errorCode": "-",
          "stage": "-",
          "upstreamStatus": "-",
          "durationMs": "-",
          "format": "structured",
          "attemptCount": "1",
          "repairApplied": "false",
          "requestId": "59459f86-a131-4319-939d-52cf1cea4b5e",
          "waitFeeling": "中",
          "elapsedMs": 4240,
          "totalDurationMs": 2137,
          "contextChars": "923",
          "finalStage": "first",
          "metaFormatReason": "structured_ok",
          "attemptDiagnostics": [
            {
              "stage": "first",
              "formatReason": "structured_ok",
              "qualityIssues": []
            }
          ],
          "firstTransportAttempts": "1",
          "firstTransportRetryApplied": "false",
          "firstTransportRetryRecovered": "false",
          "firstTransportStatuses": [
            200
          ],
          "hasUpstream503": false,
          "shortCircuitReason": "-",
          "isShortCircuit": false,
          "responseAction": "natural_answer",
          "businessIntent": "chat",
          "tonePosture": "advise",
          "expectedPosture": "advise",
          "expectedEvidenceType": "product_month",
          "isStrongDetailCase": true,
          "surfaceReply": "您应当将核心精力锁定在 1 月份的业绩回溯以及产品 B 的动销提速上，以应对 3 月环比增长乏力带来的目标缺口。\n\n从第一季度整体 88% 的达成率来看，产品 B 作为贡献了 34% 销售额的核心单品，其达成率却仅有 76%，是拖累进度的关键因素。由于目前数据仅显示 3 月份可能存在环比波动微弱的风险，您需要重点核实 1 月份启动期的铺货数据是否未达预期，并确认产品 B 在高权重渠道的真实消耗速度。\n\n建议您本周优先复盘产品 B 在 1 月份的进院明细，并针对性地对医院 D 开展二次宣讲，通过激活核心单品的存量潜力来对冲当前 80 万的业绩缺口。",
          "isNaturalCase": true,
          "isFailure": false
        },
        {
          "row": 22,
          "mode": "auto",
          "questionType": "advise",
          "http": 200,
          "errorCode": "-",
          "stage": "-",
          "upstreamStatus": "-",
          "durationMs": "-",
          "format": "structured",
          "attemptCount": "1",
          "repairApplied": "false",
          "requestId": "ff2f228f-d19c-4f1f-86a8-83a0f4ba9d48",
          "waitFeeling": "中",
          "elapsedMs": 3191,
          "totalDurationMs": 2180,
          "contextChars": "923",
          "finalStage": "first",
          "metaFormatReason": "structured_ok",
          "attemptDiagnostics": [
            {
              "stage": "first",
              "formatReason": "structured_ok",
              "qualityIssues": []
            }
          ],
          "firstTransportAttempts": "1",
          "firstTransportRetryApplied": "false",
          "firstTransportRetryRecovered": "false",
          "firstTransportStatuses": [
            200
          ],
          "hasUpstream503": false,
          "shortCircuitReason": "-",
          "isShortCircuit": false,
          "responseAction": "natural_answer",
          "businessIntent": "chat",
          "tonePosture": "judge",
          "expectedPosture": "advise",
          "expectedEvidenceType": "amount_quantity",
          "isStrongDetailCase": true,
          "surfaceReply": "您应当优先抓取产品 B 的动销提速与医院 D 的份额激活这两个核心杠杆，以实现金额与盒数的同步拉升。\n\n产品 B 作为占据 34% 销售额的核心单品，目前达成率仅为 76%，其销量的滞后是导致 80 万总缺口的主因，而医院 D 作为贡献 18% 份额的头号渠道，其 72% 的低达成率意味着巨大的存量提升空间。由于目前数据中缺失 3 月份最新的销量环比波动（quantityMom）和金额环比波动（amountMom），我们无法判断近期是否存在自然增长趋势，必须通过这两个高权重杠杆的主动干预来确保目标达成。\n\n建议您在本周内重点核实产品 B 在医院 D 的库存周转情况，并确保关键决策人的覆盖率达到 90% 以上。",
          "isNaturalCase": true,
          "isFailure": false
        },
        {
          "row": 23,
          "mode": "auto",
          "questionType": "advise",
          "http": 200,
          "errorCode": "-",
          "stage": "-",
          "upstreamStatus": "-",
          "durationMs": "-",
          "format": "structured",
          "attemptCount": "1",
          "repairApplied": "false",
          "requestId": "69cca1f9-dbca-4e59-841a-856ff3cd2843",
          "waitFeeling": "快",
          "elapsedMs": 2941,
          "totalDurationMs": 1851,
          "contextChars": "923",
          "finalStage": "first",
          "metaFormatReason": "structured_ok",
          "attemptDiagnostics": [
            {
              "stage": "first",
              "formatReason": "structured_ok",
              "qualityIssues": []
            }
          ],
          "firstTransportAttempts": "1",
          "firstTransportRetryApplied": "false",
          "firstTransportRetryRecovered": "false",
          "firstTransportStatuses": [
            200
          ],
          "hasUpstream503": false,
          "shortCircuitReason": "-",
          "isShortCircuit": false,
          "responseAction": "natural_answer",
          "businessIntent": "chat",
          "tonePosture": "judge",
          "expectedPosture": "advise",
          "expectedEvidenceType": "quantity",
          "isStrongDetailCase": true,
          "surfaceReply": "您应当立即启动对医院 D 的产品 B 专项补货计划，这是实现盒数环比 5% 增长最确定的切入点。\n\n目前医院 D 贡献了 18% 的销售份额，但其达成率仅为 72%，这种高权重、低达成的现状意味着只要该院动销回归正常水平，就能直接贡献显著的盒数增量。由于当前数据尚未更新 3 月份最新的销量环比波动（quantityMom），我们无法依赖自然增长，必须通过解决核心渠道的存量缺口来强行拉升指标。\n\n建议您本周内先核实医院 D 的实际库存水位，确保针对产品 B 的临床科室覆盖率达到 90% 以上，以确保补货后的处方转化。",
          "isNaturalCase": true,
          "isFailure": false
        },
        {
          "row": 24,
          "mode": "auto",
          "questionType": "advise",
          "http": 200,
          "errorCode": "-",
          "stage": "-",
          "upstreamStatus": "-",
          "durationMs": "-",
          "format": "structured",
          "attemptCount": "1",
          "repairApplied": "false",
          "requestId": "8298358d-9637-43af-b8dd-c04e8e3af1df",
          "waitFeeling": "快",
          "elapsedMs": 2972,
          "totalDurationMs": 2357,
          "contextChars": "923",
          "finalStage": "first",
          "metaFormatReason": "structured_ok",
          "attemptDiagnostics": [
            {
              "stage": "first",
              "formatReason": "structured_ok",
              "qualityIssues": []
            }
          ],
          "firstTransportAttempts": "1",
          "firstTransportRetryApplied": "false",
          "firstTransportRetryRecovered": "false",
          "firstTransportStatuses": [
            200
          ],
          "hasUpstream503": false,
          "shortCircuitReason": "-",
          "isShortCircuit": false,
          "responseAction": "natural_answer",
          "businessIntent": "chat",
          "tonePosture": "advise",
          "expectedPosture": "advise",
          "expectedEvidenceType": "month",
          "isStrongDetailCase": true,
          "surfaceReply": "您应当将首要动作聚焦在 2 月份的存量激活上，通过追回产品 B 在医院 D 的进度来对冲 1 月份启动不足留下的缺口。\n\n从 2 月份结束时的复盘来看，产品 B 作为贡献了 34% 销售额的核心单品，其达成率仅为 76%，是导致目前 80 万总目标缺口的最直接诱因。由于目前数据中 3 月份的金额环比（amountMom）与销量环比（quantityMom）波动尚不明确，我们必须优先解决 2 月份暴露出的结构性问题，即医院 D 仅有 72% 的低达成率。\n\n建议您本周内优先完成对医院 D 关键决策人的深度覆盖，确保针对产品 B 的临床宣讲覆盖率达到 90% 以上，以确保 3 月份能产生实质性的动销反弹。",
          "isNaturalCase": true,
          "isFailure": false
        }
      ]
    },
    {
      "inputProfile": "plus",
      "metrics": {
        "failureRate": 0,
        "timeoutRate": 0,
        "attempt3Rate": 0,
        "structuredRate": 1,
        "finalStageFirstRate": 1,
        "finalStageRetryRate": 0,
        "finalStageRepairRate": 0,
        "p50ElapsedMs": 2819,
        "p95ElapsedMs": 3853
      },
      "checks": [
        {
          "label": "总失败率 <= 20%",
          "value": "0.0%",
          "pass": true
        },
        {
          "label": "UPSTREAM_TIMEOUT 占比 <= 10%",
          "value": "0.0%",
          "pass": true
        },
        {
          "label": "attemptCount=3 占比 <= 30%",
          "value": "0.0%",
          "pass": true
        },
        {
          "label": "structured 占比 >= 60%",
          "value": "100.0%",
          "pass": true
        },
        {
          "label": "structured 相对 baseline 下滑 <= 10pp",
          "value": "+50.0pp",
          "pass": true
        },
        {
          "label": "p95 elapsedMs <= 15000ms",
          "value": "3853ms",
          "pass": true
        },
        {
          "label": "profile 未被鉴权中断",
          "value": "ok",
          "pass": true
        },
        {
          "label": "real-context 有效性（shortCircuitRate <= 20.0%）",
          "value": "0.0%",
          "pass": true
        },
        {
          "label": "naturalRouteRate >= 80%",
          "value": "100.0%",
          "pass": true
        },
        {
          "label": "postureMatchRate >= 85%",
          "value": "91.7%",
          "pass": true
        },
        {
          "label": "gapHintOverfireRate <= 10%",
          "value": "0.0%",
          "pass": true
        }
      ],
      "experimentValidity": {
        "valid": true,
        "reason": "ok",
        "shortCircuitRate": 0,
        "threshold": 0.2
      },
      "execution": {
        "plannedCount": 24,
        "executedCount": 24,
        "aborted": false,
        "abortReason": "",
        "valid": true
      },
      "naturalQuality": {
        "enabled": true,
        "total": 24,
        "naturalRouteRate": 1,
        "postureMatchRate": 0.9166666666666666,
        "gapHintOverfireRate": 0,
        "evidenceMentionRate": 1,
        "detailNumericAnswerRate": 1,
        "detailClarifyRate": 0,
        "detailEvidenceCoverageRate": 0.9166666666666666,
        "counts": {
          "naturalRouteCount": 24,
          "postureEligibleCount": 24,
          "postureMatchCount": 22,
          "judgeCaseCount": 8,
          "gapHintOverfireCount": 0,
          "evidenceMentionCount": 24,
          "detailCaseCount": 12,
          "detailClarifyCount": 0,
          "detailNumericAnswerCount": 12,
          "detailEvidenceCoverageCount": 11
        },
        "byPosture": [
          {
            "posture": "judge",
            "total": 8,
            "matchRate": 1
          },
          {
            "posture": "explain",
            "total": 8,
            "matchRate": 1
          },
          {
            "posture": "advise",
            "total": 8,
            "matchRate": 0.75
          }
        ]
      },
      "modeStats": [
        {
          "mode": "auto",
          "total": 24,
          "attempt3Rate": 0,
          "textFallbackRate": 0,
          "finalStageFirstRate": 1,
          "finalStageRetryRate": 0,
          "finalStageRepairRate": 0,
          "firstTransportRetryAppliedRate": 0,
          "firstTransportRetryRecoveredRate": 0,
          "upstream503Rate": 0,
          "p95ElapsedMs": 3853
        }
      ],
      "firstHitQuality": {
        "overall": {
          "firstStructuredOkRate": 1,
          "firstOutputTruncatedRate": 0
        },
        "byMode": [
          {
            "mode": "auto",
            "total": 24,
            "firstStructuredOkRate": 1,
            "firstOutputTruncatedRate": 0
          }
        ]
      },
      "contextCharStats": {
        "count": 24,
        "p50": 1201,
        "p95": 1201
      },
      "results": [
        {
          "row": 1,
          "mode": "auto",
          "questionType": "judge",
          "http": 200,
          "errorCode": "-",
          "stage": "-",
          "upstreamStatus": "-",
          "durationMs": "-",
          "format": "structured",
          "attemptCount": "1",
          "repairApplied": "false",
          "requestId": "6877b6a2-3261-440c-8673-9f9b7a8e4199",
          "waitFeeling": "快",
          "elapsedMs": 2443,
          "totalDurationMs": 1754,
          "contextChars": "1201",
          "finalStage": "first",
          "metaFormatReason": "structured_ok",
          "attemptDiagnostics": [
            {
              "stage": "first",
              "formatReason": "structured_ok",
              "qualityIssues": []
            }
          ],
          "firstTransportAttempts": "1",
          "firstTransportRetryApplied": "false",
          "firstTransportRetryRecovered": "false",
          "firstTransportStatuses": [
            200
          ],
          "hasUpstream503": false,
          "shortCircuitReason": "-",
          "isShortCircuit": false,
          "responseAction": "natural_answer",
          "businessIntent": "chat",
          "tonePosture": "judge",
          "expectedPosture": "judge",
          "expectedEvidenceType": "none",
          "isStrongDetailCase": false,
          "surfaceReply": "本月销售表现呈现出“微增但未达标”的态势，整体增长动能略显不足。\n\n虽然销售额同比小幅增长了2.7%，但目前88.13%的达成率距离季度目标仍有约12%的缺口。这一判断主要基于2026年第一季度的整体表现，目前数据尚未覆盖到具体的区域或细分科室的产出情况。\n\n您是否需要重点查看达成率较低的产品B或医院D的具体销售明细？",
          "isNaturalCase": true,
          "isFailure": false
        },
        {
          "row": 2,
          "mode": "auto",
          "questionType": "judge",
          "http": 200,
          "errorCode": "-",
          "stage": "-",
          "upstreamStatus": "-",
          "durationMs": "-",
          "format": "structured",
          "attemptCount": "1",
          "repairApplied": "false",
          "requestId": "59208664-c51f-4c19-896e-804e62d02130",
          "waitFeeling": "中",
          "elapsedMs": 3475,
          "totalDurationMs": 1964,
          "contextChars": "1201",
          "finalStage": "first",
          "metaFormatReason": "structured_ok",
          "attemptDiagnostics": [
            {
              "stage": "first",
              "formatReason": "structured_ok",
              "qualityIssues": []
            }
          ],
          "firstTransportAttempts": "1",
          "firstTransportRetryApplied": "false",
          "firstTransportRetryRecovered": "false",
          "firstTransportStatuses": [
            200
          ],
          "hasUpstream503": false,
          "shortCircuitReason": "-",
          "isShortCircuit": false,
          "responseAction": "natural_answer",
          "businessIntent": "chat",
          "tonePosture": "judge",
          "expectedPosture": "judge",
          "expectedEvidenceType": "none",
          "isStrongDetailCase": false,
          "surfaceReply": "从近两个月的动态来看，整体销售正处于从快速回升向增速趋稳过渡的承压阶段。\n\n虽然 2 月份销售额环比显著恢复了 6.2%，但进入 3 月后环比增速已放缓至 2.1%，增长动能的减弱使得季度达成率依然停留在 88.13% 的低位。目前的分析主要聚焦于季度内的月度波动，尚未深入到各周的具体波动细节。\n\n您是否想了解 3 月增速放缓是受特定产品 B 的影响，还是重点医院 D 的采购节奏有所调整？",
          "isNaturalCase": true,
          "isFailure": false
        },
        {
          "row": 3,
          "mode": "auto",
          "questionType": "judge",
          "http": 200,
          "errorCode": "-",
          "stage": "-",
          "upstreamStatus": "-",
          "durationMs": "-",
          "format": "structured",
          "attemptCount": "1",
          "repairApplied": "false",
          "requestId": "43c02176-ebf0-4443-8768-26f7f17b0a66",
          "waitFeeling": "快",
          "elapsedMs": 2446,
          "totalDurationMs": 1816,
          "contextChars": "1201",
          "finalStage": "first",
          "metaFormatReason": "structured_ok",
          "attemptDiagnostics": [
            {
              "stage": "first",
              "formatReason": "structured_ok",
              "qualityIssues": []
            }
          ],
          "firstTransportAttempts": "1",
          "firstTransportRetryApplied": "false",
          "firstTransportRetryRecovered": "false",
          "firstTransportStatuses": [
            200
          ],
          "hasUpstream503": false,
          "shortCircuitReason": "-",
          "isShortCircuit": false,
          "responseAction": "natural_answer",
          "businessIntent": "chat",
          "tonePosture": "judge",
          "expectedPosture": "judge",
          "expectedEvidenceType": "none",
          "isStrongDetailCase": false,
          "surfaceReply": "目前的达成率状态并不理想，正处于需要警惕的亚健康区间。\n\n虽然季度销售额已达到 581.6 万元，但 88.13% 的达成率意味着我们仍面临约 12% 的业绩缺口，且 3 月份 2.1% 的环比增速明显放缓，难以支撑季度末的强力冲刺。目前的评估主要基于 2026 年第一季度的整体 KPI，尚未包含 4 月份的最新预估数据。\n\n您是否需要针对达成率仅为 76% 的核心产品 B，制定专项的补缺计划？",
          "isNaturalCase": true,
          "isFailure": false
        },
        {
          "row": 4,
          "mode": "auto",
          "questionType": "judge",
          "http": 200,
          "errorCode": "-",
          "stage": "-",
          "upstreamStatus": "-",
          "durationMs": "-",
          "format": "structured",
          "attemptCount": "1",
          "repairApplied": "false",
          "requestId": "90adb667-72c2-4b42-b1a6-3ee5cb21f3d7",
          "waitFeeling": "快",
          "elapsedMs": 2680,
          "totalDurationMs": 2130,
          "contextChars": "1201",
          "finalStage": "first",
          "metaFormatReason": "structured_ok",
          "attemptDiagnostics": [
            {
              "stage": "first",
              "formatReason": "structured_ok",
              "qualityIssues": []
            }
          ],
          "firstTransportAttempts": "1",
          "firstTransportRetryApplied": "false",
          "firstTransportRetryRecovered": "false",
          "firstTransportStatuses": [
            200
          ],
          "hasUpstream503": false,
          "shortCircuitReason": "-",
          "isShortCircuit": false,
          "responseAction": "natural_answer",
          "businessIntent": "chat",
          "tonePosture": "judge",
          "expectedPosture": "judge",
          "expectedEvidenceType": "none",
          "isStrongDetailCase": false,
          "surfaceReply": "当前的业绩风险确实较大，已经触及了季度目标能否如期兑现的红线。\n\n最核心的风险依据在于，目前 88.13% 的达成率意味着在季度末仍存在约 78.4 万元的业绩缺口，而 3 月份销售额环比增速已收窄至 2.1%，这种增长惯性很难在剩余时间内填补缺口。目前的风险评估主要聚焦于第一季度的财务达成，尚未将供应链库存或竞品动态纳入考量。\n\n您是否需要重点排查达成率仅为 72% 的医院 D，看看是否是该核心客户的采购进度拖累了整体进度？",
          "isNaturalCase": true,
          "isFailure": false
        },
        {
          "row": 5,
          "mode": "auto",
          "questionType": "judge",
          "http": 200,
          "errorCode": "-",
          "stage": "-",
          "upstreamStatus": "-",
          "durationMs": "-",
          "format": "structured",
          "attemptCount": "1",
          "repairApplied": "false",
          "requestId": "49870ff0-21f1-47c8-8893-6589b5284a3d",
          "waitFeeling": "快",
          "elapsedMs": 2295,
          "totalDurationMs": 1811,
          "contextChars": "1201",
          "finalStage": "first",
          "metaFormatReason": "structured_ok",
          "attemptDiagnostics": [
            {
              "stage": "first",
              "formatReason": "structured_ok",
              "qualityIssues": []
            }
          ],
          "firstTransportAttempts": "1",
          "firstTransportRetryApplied": "false",
          "firstTransportRetryRecovered": "false",
          "firstTransportStatuses": [
            200
          ],
          "hasUpstream503": false,
          "shortCircuitReason": "-",
          "isShortCircuit": false,
          "responseAction": "natural_answer",
          "businessIntent": "chat",
          "tonePosture": "judge",
          "expectedPosture": "judge",
          "expectedEvidenceType": "month",
          "isStrongDetailCase": true,
          "surfaceReply": "最近两个月的环比波动呈现出明显的收窄趋势，整体波动幅度较大且增长动能正在减弱。\n\n2 月份销售额环比显著回升了 6.2%，但进入 3 月后环比增速已放缓至 2.1%，这种增速的快速下滑反映出市场回暖的后劲不足。目前的波动分析仅基于 2 月和 3 月的金额数据，尚未结合同期销量环比进行量价协同评估。\n\n您是否需要对比一下 3 月份销量的环比变化，以确认增速放缓是由于单价调整还是采购量下降导致的？",
          "isNaturalCase": true,
          "isFailure": false
        },
        {
          "row": 6,
          "mode": "auto",
          "questionType": "judge",
          "http": 200,
          "errorCode": "-",
          "stage": "-",
          "upstreamStatus": "-",
          "durationMs": "-",
          "format": "structured",
          "attemptCount": "1",
          "repairApplied": "false",
          "requestId": "67187451-18ba-4e67-93f8-111b996badaa",
          "waitFeeling": "快",
          "elapsedMs": 2159,
          "totalDurationMs": 1658,
          "contextChars": "1201",
          "finalStage": "first",
          "metaFormatReason": "structured_ok",
          "attemptDiagnostics": [
            {
              "stage": "first",
              "formatReason": "structured_ok",
              "qualityIssues": []
            }
          ],
          "firstTransportAttempts": "1",
          "firstTransportRetryApplied": "false",
          "firstTransportRetryRecovered": "false",
          "firstTransportStatuses": [
            200
          ],
          "hasUpstream503": false,
          "shortCircuitReason": "-",
          "isShortCircuit": false,
          "responseAction": "natural_answer",
          "businessIntent": "chat",
          "tonePosture": "judge",
          "expectedPosture": "judge",
          "expectedEvidenceType": "quantity",
          "isStrongDetailCase": true,
          "surfaceReply": "本季度销量盒数呈现上升态势，整体表现出“量增快于额增”的特征。\n\n根据一季度业务数据显示，当前总销量已达到 12.43 万盒，且 2 月份销量环比增长了 8%，3 月份继续保持了 8% 的环比增长。目前的销量评估仅涵盖了 2026 年第一季度的总量与环比波动，尚未包含各产品规格的具体销量分布数据。\n\n您是否需要进一步核实，销量增速高于销售额增速是否是因为单价较低的产品 B 在结构中占比过高导致的？",
          "isNaturalCase": true,
          "isFailure": false
        },
        {
          "row": 7,
          "mode": "auto",
          "questionType": "judge",
          "http": 200,
          "errorCode": "-",
          "stage": "-",
          "upstreamStatus": "-",
          "durationMs": "-",
          "format": "structured",
          "attemptCount": "1",
          "repairApplied": "false",
          "requestId": "61c9de0a-6cd6-493d-9578-89f47bd6e541",
          "waitFeeling": "快",
          "elapsedMs": 2561,
          "totalDurationMs": 2033,
          "contextChars": "1201",
          "finalStage": "first",
          "metaFormatReason": "structured_ok",
          "attemptDiagnostics": [
            {
              "stage": "first",
              "formatReason": "structured_ok",
              "qualityIssues": []
            }
          ],
          "firstTransportAttempts": "1",
          "firstTransportRetryApplied": "false",
          "firstTransportRetryRecovered": "false",
          "firstTransportStatuses": [
            200
          ],
          "hasUpstream503": false,
          "shortCircuitReason": "-",
          "isShortCircuit": false,
          "responseAction": "natural_answer",
          "businessIntent": "chat",
          "tonePosture": "judge",
          "expectedPosture": "judge",
          "expectedEvidenceType": "amount_quantity",
          "isStrongDetailCase": true,
          "surfaceReply": "本季度金额与盒数在增长方向上保持一致，但二者的增长步调并不完全同步。\n\n从趋势上看，3 月份销售额环比增长了 2.1%，而同期销量盒数则保持了 8% 的环比增幅，这种“量增额微增”的背离意味着单价较低的产品在销售结构中占据了主导。目前的同向性判断仅基于一季度整体趋势，尚未剔除促销活动或大客户返利对单价造成的短期干扰。\n\n您是否需要调取各产品的单价变动明细，以确认销售额增速滞后是否由核心产品 B 的价格波动引起？",
          "isNaturalCase": true,
          "isFailure": false
        },
        {
          "row": 8,
          "mode": "auto",
          "questionType": "judge",
          "http": 200,
          "errorCode": "-",
          "stage": "-",
          "upstreamStatus": "-",
          "durationMs": "-",
          "format": "structured",
          "attemptCount": "1",
          "repairApplied": "false",
          "requestId": "64456ecc-5d4c-4688-88be-65682712167c",
          "waitFeeling": "快",
          "elapsedMs": 2550,
          "totalDurationMs": 2089,
          "contextChars": "1201",
          "finalStage": "first",
          "metaFormatReason": "structured_ok",
          "attemptDiagnostics": [
            {
              "stage": "first",
              "formatReason": "structured_ok",
              "qualityIssues": []
            }
          ],
          "firstTransportAttempts": "1",
          "firstTransportRetryApplied": "false",
          "firstTransportRetryRecovered": "false",
          "firstTransportStatuses": [
            200
          ],
          "hasUpstream503": false,
          "shortCircuitReason": "-",
          "isShortCircuit": false,
          "responseAction": "natural_answer",
          "businessIntent": "chat",
          "tonePosture": "judge",
          "expectedPosture": "judge",
          "expectedEvidenceType": "product_month",
          "isStrongDetailCase": true,
          "surfaceReply": "目前最拖累业绩的是产品 B，而 3 月份的增长乏力则在时间维度上最为不利。\n\n产品 B 虽然贡献了 34% 的销售份额，但其达成率仅为 76%，远低于平均水平；同时 3 月份销售额环比增速从 2 月的 6.2% 骤降至 2.1%，直接导致了季度末的业绩缺口。目前的判断主要聚焦于产品达成率与月度环比趋势，暂未获取 1 月份的具体环比波动数据。\n\n您是否需要针对产品 B 在 3 月份的进院情况进行专项分析，以确认其增速放缓是否与核心医院的采购周期有关？",
          "isNaturalCase": true,
          "isFailure": false
        },
        {
          "row": 9,
          "mode": "auto",
          "questionType": "explain",
          "http": 200,
          "errorCode": "-",
          "stage": "-",
          "upstreamStatus": "-",
          "durationMs": "-",
          "format": "structured",
          "attemptCount": "1",
          "repairApplied": "false",
          "requestId": "ee38cf8f-2050-4110-9da2-8561fb6dc8ec",
          "waitFeeling": "快",
          "elapsedMs": 2827,
          "totalDurationMs": 2387,
          "contextChars": "1201",
          "finalStage": "first",
          "metaFormatReason": "structured_ok",
          "attemptDiagnostics": [
            {
              "stage": "first",
              "formatReason": "structured_ok",
              "qualityIssues": []
            }
          ],
          "firstTransportAttempts": "1",
          "firstTransportRetryApplied": "false",
          "firstTransportRetryRecovered": "false",
          "firstTransportStatuses": [
            200
          ],
          "hasUpstream503": false,
          "shortCircuitReason": "-",
          "isShortCircuit": false,
          "responseAction": "natural_answer",
          "businessIntent": "chat",
          "tonePosture": "explain",
          "expectedPosture": "explain",
          "expectedEvidenceType": "none",
          "isStrongDetailCase": false,
          "surfaceReply": "本季度未能达成目标主要是受核心产品表现疲软与重点医院推进效率低下的双重拖累。\n\n尽管整体销售额达到 581.6 万元，但 88.1% 的达成率意味着仍存在约 12% 的业绩缺口，尤其是贡献了 34% 份额的产品 B 达成率仅为 76%，且 3 月份销售额环比增速已大幅放缓至 2.1%。目前的分析结论主要基于一季度整体汇总数据，尚未包含 1 月份具体的环比波动细节。\n\n您是否需要针对达成率仅为 72% 的医院 D 进行专项复盘，以确认其采购停滞是否是导致产品 B 业绩缺口的主因？",
          "isNaturalCase": true,
          "isFailure": false
        },
        {
          "row": 10,
          "mode": "auto",
          "questionType": "explain",
          "http": 200,
          "errorCode": "-",
          "stage": "-",
          "upstreamStatus": "-",
          "durationMs": "-",
          "format": "structured",
          "attemptCount": "1",
          "repairApplied": "false",
          "requestId": "f4237827-feb4-4aa2-9682-721982a3dfea",
          "waitFeeling": "快",
          "elapsedMs": 2949,
          "totalDurationMs": 2219,
          "contextChars": "1201",
          "finalStage": "first",
          "metaFormatReason": "structured_ok",
          "attemptDiagnostics": [
            {
              "stage": "first",
              "formatReason": "structured_ok",
              "qualityIssues": []
            }
          ],
          "firstTransportAttempts": "1",
          "firstTransportRetryApplied": "false",
          "firstTransportRetryRecovered": "false",
          "firstTransportStatuses": [
            200
          ],
          "hasUpstream503": false,
          "shortCircuitReason": "-",
          "isShortCircuit": false,
          "responseAction": "natural_answer",
          "businessIntent": "chat",
          "tonePosture": "explain",
          "expectedPosture": "explain",
          "expectedEvidenceType": "none",
          "isStrongDetailCase": false,
          "surfaceReply": "近期增长放缓的核心原因在于核心产品在重点医院的推进受阻，导致季度末的增长动能明显衰减。\n\n从数据来看，3 月份销售额环比增速从 2 月的 6.2% 大幅回落至 2.1%，这种放缓直接受累于贡献了 18% 份额的医院 D 达成率仅为 72%，以及主力产品 B 远低于平均水平的 76% 达成率。目前的分析主要聚焦于 2 月和 3 月的环比波动，由于缺乏 1 月份的具体环比数据，尚无法完整还原整个季度的波动全貌。\n\n您是否需要针对医院 D 的采购流程进行深度穿透，以确认 3 月份的增速骤降是否由该院的招标延迟或库存积压所致？",
          "isNaturalCase": true,
          "isFailure": false
        },
        {
          "row": 11,
          "mode": "auto",
          "questionType": "explain",
          "http": 200,
          "errorCode": "-",
          "stage": "-",
          "upstreamStatus": "-",
          "durationMs": "-",
          "format": "structured",
          "attemptCount": "1",
          "repairApplied": "false",
          "requestId": "f48f21d7-82f3-4463-a37f-4fcea93fa914",
          "waitFeeling": "中",
          "elapsedMs": 4631,
          "totalDurationMs": 1888,
          "contextChars": "1201",
          "finalStage": "first",
          "metaFormatReason": "structured_ok",
          "attemptDiagnostics": [
            {
              "stage": "first",
              "formatReason": "structured_ok",
              "qualityIssues": []
            }
          ],
          "firstTransportAttempts": "1",
          "firstTransportRetryApplied": "false",
          "firstTransportRetryRecovered": "false",
          "firstTransportStatuses": [
            200
          ],
          "hasUpstream503": false,
          "shortCircuitReason": "-",
          "isShortCircuit": false,
          "responseAction": "natural_answer",
          "businessIntent": "chat",
          "tonePosture": "explain",
          "expectedPosture": "explain",
          "expectedEvidenceType": "none",
          "isStrongDetailCase": false,
          "surfaceReply": "业绩风险未能显著下降，主要源于核心增长引擎的动力持续减弱，导致季度末的缺口无法被有效填补。\n\n虽然 2 月份曾出现 6.2% 的环比回升，但 3 月份销售额环比增速又回落至 2.1%，这种增速的再次放缓使得整体达成率停留在 88.1%，始终无法跨越 12% 的业绩红线。目前的风险评估主要基于一季度已发生的销售数据，尚未将下季度预期的招标增量或新入院计划纳入计算。\n\n您是否需要查看下周针对医院 D 和医院 F 的专项推进计划，以评估这些重点客户的突破能否在短期内对冲目前的达成风险？",
          "isNaturalCase": true,
          "isFailure": false
        },
        {
          "row": 12,
          "mode": "auto",
          "questionType": "explain",
          "http": 200,
          "errorCode": "-",
          "stage": "-",
          "upstreamStatus": "-",
          "durationMs": "-",
          "format": "structured",
          "attemptCount": "1",
          "repairApplied": "false",
          "requestId": "b1673630-4ebe-43e6-ba3b-69774033717e",
          "waitFeeling": "中",
          "elapsedMs": 3164,
          "totalDurationMs": 2185,
          "contextChars": "1201",
          "finalStage": "first",
          "metaFormatReason": "structured_ok",
          "attemptDiagnostics": [
            {
              "stage": "first",
              "formatReason": "structured_ok",
              "qualityIssues": []
            }
          ],
          "firstTransportAttempts": "1",
          "firstTransportRetryApplied": "false",
          "firstTransportRetryRecovered": "false",
          "firstTransportStatuses": [
            200
          ],
          "hasUpstream503": false,
          "shortCircuitReason": "-",
          "isShortCircuit": false,
          "responseAction": "natural_answer",
          "businessIntent": "chat",
          "tonePosture": "explain",
          "expectedPosture": "explain",
          "expectedEvidenceType": "none",
          "isStrongDetailCase": false,
          "surfaceReply": "当前的压力主要源于回升势头在季度末出现了明显的边际递减，导致前期积累的业绩缺口未能被及时抹平。\n\n虽然 2 月份销售额环比增长了 6.2%，展现了良好的修复迹象，但进入 3 月后环比增速却收窄至 2.1%，这种增长后劲不足直接导致整体达成率仍停留在 88.1% 的低位。目前的判断主要基于一季度已完成的销售趋势，尚未将后续可能落地的招标增量或新入院计划纳入评估。\n\n您是否需要重点调取 3 月份环比增速放缓最明显的几家医院名单，以确认这种趋势回落是受季节性因素影响还是竞争环境发生了变化？",
          "isNaturalCase": true,
          "isFailure": false
        },
        {
          "row": 13,
          "mode": "auto",
          "questionType": "explain",
          "http": 200,
          "errorCode": "-",
          "stage": "-",
          "upstreamStatus": "-",
          "durationMs": "-",
          "format": "structured",
          "attemptCount": "1",
          "repairApplied": "false",
          "requestId": "37362b91-a802-4a01-91dc-dd801b5a48df",
          "waitFeeling": "快",
          "elapsedMs": 2649,
          "totalDurationMs": 2156,
          "contextChars": "1201",
          "finalStage": "first",
          "metaFormatReason": "structured_ok",
          "attemptDiagnostics": [
            {
              "stage": "first",
              "formatReason": "structured_ok",
              "qualityIssues": []
            }
          ],
          "firstTransportAttempts": "1",
          "firstTransportRetryApplied": "false",
          "firstTransportRetryRecovered": "false",
          "firstTransportStatuses": [
            200
          ],
          "hasUpstream503": false,
          "shortCircuitReason": "-",
          "isShortCircuit": false,
          "responseAction": "natural_answer",
          "businessIntent": "chat",
          "tonePosture": "explain",
          "expectedPosture": "explain",
          "expectedEvidenceType": "month",
          "isStrongDetailCase": true,
          "surfaceReply": "环比增幅的收窄主要是因为 3 月份的增长动能未能延续 2 月份的强劲修复态势，导致增速出现了 4.1 个百分点的明显回落。\n\n从数据来看，2 月份销售额环比增长了 6.2%，而 3 月份的环比增速仅为 2.1%，这种增长后劲的不足直接受累于贡献了 18% 份额的医院 D 达成率仅为 72%。目前的分析主要聚焦于 2 月与 3 月的环比波动对比，尚未包含 3 月份具体的销量环比数据，无法判断这种增幅收窄是受单价波动还是采购量下滑的影响。\n\n您是否需要对比 3 月份各核心产品的销量环比变化，以确认增速放缓是否由主力产品 B 的需求波动所致？",
          "isNaturalCase": true,
          "isFailure": false
        },
        {
          "row": 14,
          "mode": "auto",
          "questionType": "explain",
          "http": 200,
          "errorCode": "-",
          "stage": "-",
          "upstreamStatus": "-",
          "durationMs": "-",
          "format": "structured",
          "attemptCount": "1",
          "repairApplied": "false",
          "requestId": "05fdeab1-a5ca-40b9-b01f-4abf51ba1313",
          "waitFeeling": "快",
          "elapsedMs": 2819,
          "totalDurationMs": 2264,
          "contextChars": "1201",
          "finalStage": "first",
          "metaFormatReason": "structured_ok",
          "attemptDiagnostics": [
            {
              "stage": "first",
              "formatReason": "structured_ok",
              "qualityIssues": []
            }
          ],
          "firstTransportAttempts": "1",
          "firstTransportRetryApplied": "false",
          "firstTransportRetryRecovered": "false",
          "firstTransportStatuses": [
            200
          ],
          "hasUpstream503": false,
          "shortCircuitReason": "-",
          "isShortCircuit": false,
          "responseAction": "natural_answer",
          "businessIntent": "chat",
          "tonePosture": "explain",
          "expectedPosture": "explain",
          "expectedEvidenceType": "amount_quantity",
          "isStrongDetailCase": true,
          "surfaceReply": "这种背离现象主要是因为产品销售结构发生了变化，低单价产品或折扣力度的增加导致了“量增额不增”的局面。\n\n从数据来看，虽然一季度销量达到了 12.43 万盒，展现出较强的规模扩张，但销售额仅实现 581.6 万元，且 3 月份的金额环比增速已从 2 月的 6.2% 明显回落至 2.1%。目前的分析主要基于整体的量额对比，由于缺乏各规格产品的具体价格波动数据，尚无法精准定位是由于主力产品 B 的单价下调还是低价位产品的占比提升所致。\n\n您是否需要调取不同单价区间产品的销量占比变化，以确认这种趋势是否由高价值产品的份额流失引起的？",
          "isNaturalCase": true,
          "isFailure": false
        },
        {
          "row": 15,
          "mode": "auto",
          "questionType": "explain",
          "http": 200,
          "errorCode": "-",
          "stage": "-",
          "upstreamStatus": "-",
          "durationMs": "-",
          "format": "structured",
          "attemptCount": "1",
          "repairApplied": "false",
          "requestId": "61897d76-eecf-4f6c-aa7c-75815239aaef",
          "waitFeeling": "快",
          "elapsedMs": 2661,
          "totalDurationMs": 2180,
          "contextChars": "1201",
          "finalStage": "first",
          "metaFormatReason": "structured_ok",
          "attemptDiagnostics": [
            {
              "stage": "first",
              "formatReason": "structured_ok",
              "qualityIssues": []
            }
          ],
          "firstTransportAttempts": "1",
          "firstTransportRetryApplied": "false",
          "firstTransportRetryRecovered": "false",
          "firstTransportStatuses": [
            200
          ],
          "hasUpstream503": false,
          "shortCircuitReason": "-",
          "isShortCircuit": false,
          "responseAction": "natural_answer",
          "businessIntent": "chat",
          "tonePosture": "explain",
          "expectedPosture": "explain",
          "expectedEvidenceType": "product_month",
          "isStrongDetailCase": true,
          "surfaceReply": "3月部分产品销量下滑明显，核心原因在于主力产品B的增长动能严重不足，其较低的达成率直接拖累了整体的放量节奏。\n\n从业务表现看，产品B作为贡献了34%份额的核心品种，其达成率仅为76%，这种大单品的疲软导致3月整体销售额环比增速从2月的6.2%骤降至2.1%。目前的分析主要基于产品维度的达成情况，由于缺乏3月份各产品具体的销量环比（quantityMom）数据，尚无法量化特定产品在当月的确切掉量规模。\n\n您是否需要进一步核查产品B在医院D等核心渠道的进院及库存情况，以确认掉量是由于终端需求萎缩还是供应链配送延迟导致的？",
          "isNaturalCase": true,
          "isFailure": false
        },
        {
          "row": 16,
          "mode": "auto",
          "questionType": "explain",
          "http": 200,
          "errorCode": "-",
          "stage": "-",
          "upstreamStatus": "-",
          "durationMs": "-",
          "format": "structured",
          "attemptCount": "1",
          "repairApplied": "false",
          "requestId": "30c79366-5b42-4c53-a82d-e296d69bb2d4",
          "waitFeeling": "中",
          "elapsedMs": 3732,
          "totalDurationMs": 2234,
          "contextChars": "1201",
          "finalStage": "first",
          "metaFormatReason": "structured_ok",
          "attemptDiagnostics": [
            {
              "stage": "first",
              "formatReason": "structured_ok",
              "qualityIssues": []
            }
          ],
          "firstTransportAttempts": "1",
          "firstTransportRetryApplied": "false",
          "firstTransportRetryRecovered": "false",
          "firstTransportStatuses": [
            200
          ],
          "hasUpstream503": false,
          "shortCircuitReason": "-",
          "isShortCircuit": false,
          "responseAction": "natural_answer",
          "businessIntent": "chat",
          "tonePosture": "explain",
          "expectedPosture": "explain",
          "expectedEvidenceType": "product",
          "isStrongDetailCase": true,
          "surfaceReply": "核心产品贡献未能持续抬升，主要受制于占据 34% 份额的主力产品 B 表现疲软，其较低的达成水平抵消了其他产品的增长红利。\n\n从业务数据看，产品 B 的达成率仅为 76%，远低于整体 88.1% 的平均水平，这直接导致 3 月份的销售额环比增速从 2 月的 6.2% 快速收窄至 2.1%。目前的分析主要聚焦于一季度的累计达成情况，由于缺乏 3 月份各核心产品具体的销量环比数据，尚无法判断这种贡献停滞是由于终端处方量萎缩还是受竞品挤压所致。\n\n您是否需要对比产品 B 与产品 D 在核心医院的覆盖率变化，以确认贡献受阻是否与特定渠道的准入进度有关？",
          "isNaturalCase": true,
          "isFailure": false
        },
        {
          "row": 17,
          "mode": "auto",
          "questionType": "advise",
          "http": 200,
          "errorCode": "-",
          "stage": "-",
          "upstreamStatus": "-",
          "durationMs": "-",
          "format": "structured",
          "attemptCount": "1",
          "repairApplied": "false",
          "requestId": "6bcec6f6-3dd7-4722-96ab-be5fd3e6a7fc",
          "waitFeeling": "快",
          "elapsedMs": 2687,
          "totalDurationMs": 2212,
          "contextChars": "1201",
          "finalStage": "first",
          "metaFormatReason": "structured_ok",
          "attemptDiagnostics": [
            {
              "stage": "first",
              "formatReason": "structured_ok",
              "qualityIssues": []
            }
          ],
          "firstTransportAttempts": "1",
          "firstTransportRetryApplied": "false",
          "firstTransportRetryRecovered": "false",
          "firstTransportStatuses": [
            200
          ],
          "hasUpstream503": false,
          "shortCircuitReason": "-",
          "isShortCircuit": false,
          "responseAction": "natural_answer",
          "businessIntent": "chat",
          "tonePosture": "advise",
          "expectedPosture": "advise",
          "expectedEvidenceType": "none",
          "isStrongDetailCase": false,
          "surfaceReply": "建议您立即针对贡献度最高但达成率偏低的产品 B，启动对医院 D 等核心渠道的专项推进动作。\n\n从业务现状看，产品 B 占据了 34% 的份额却仅实现 76% 的达成率，而其核心阵地医院 D 的达成率也只有 72%，这直接拖累了整体 88.1% 的目标进度。目前的行动建议主要基于一季度累计的份额与达成缺口，由于缺乏 3 月份各医院具体的销量环比数据，尚无法精准判定近期波动是受竞品准入影响还是纯粹的采购周期调整。\n\n您是否需要我为您梳理一份针对医院 D 的产品 B 专项跟进清单，以确保在下周五前完成关键决策人的会谈？",
          "isNaturalCase": true,
          "isFailure": false
        },
        {
          "row": 18,
          "mode": "auto",
          "questionType": "advise",
          "http": 200,
          "errorCode": "-",
          "stage": "-",
          "upstreamStatus": "-",
          "durationMs": "-",
          "format": "structured",
          "attemptCount": "1",
          "repairApplied": "false",
          "requestId": "62ee2854-26ca-4ff4-98f7-d612bd8d2300",
          "waitFeeling": "中",
          "elapsedMs": 3853,
          "totalDurationMs": 2320,
          "contextChars": "1201",
          "finalStage": "first",
          "metaFormatReason": "structured_ok",
          "attemptDiagnostics": [
            {
              "stage": "first",
              "formatReason": "structured_ok",
              "qualityIssues": []
            }
          ],
          "firstTransportAttempts": "1",
          "firstTransportRetryApplied": "false",
          "firstTransportRetryRecovered": "false",
          "firstTransportStatuses": [
            200
          ],
          "hasUpstream503": false,
          "shortCircuitReason": "-",
          "isShortCircuit": false,
          "responseAction": "natural_answer",
          "businessIntent": "chat",
          "tonePosture": "advise",
          "expectedPosture": "advise",
          "expectedEvidenceType": "none",
          "isStrongDetailCase": false,
          "surfaceReply": "您本周应优先针对达成率仅为 72% 的核心渠道医院 D，开展关于产品 B 的专项准入与上量沟通。\n\n目前产品 B 占据了 34% 的最高份额，但其 76% 的达成率远低于 88.1% 的平均水平，且 3 月份整体销售额环比增速已从 2 月的 6.2% 明显收窄至 2.1%。当前的改进建议主要聚焦于高价值缺口的修复，由于缺乏 3 月份各医院具体的销量环比数据，尚无法判定医院 D 的进度滞后是受竞品干扰还是采购流程的短期波动。\n\n建议您在下周五前完成对医院 D 关键决策人的深度拜访，并确认是否需要我为您整理该医院近三个月的规格级进货趋势以辅助谈判？",
          "isNaturalCase": true,
          "isFailure": false
        },
        {
          "row": 19,
          "mode": "auto",
          "questionType": "advise",
          "http": 200,
          "errorCode": "-",
          "stage": "-",
          "upstreamStatus": "-",
          "durationMs": "-",
          "format": "structured",
          "attemptCount": "1",
          "repairApplied": "false",
          "requestId": "438b7902-df3a-4a0d-b629-bd4d8d33ebf9",
          "waitFeeling": "快",
          "elapsedMs": 2741,
          "totalDurationMs": 1932,
          "contextChars": "1201",
          "finalStage": "first",
          "metaFormatReason": "structured_ok",
          "attemptDiagnostics": [
            {
              "stage": "first",
              "formatReason": "structured_ok",
              "qualityIssues": []
            }
          ],
          "firstTransportAttempts": "1",
          "firstTransportRetryApplied": "false",
          "firstTransportRetryRecovered": "false",
          "firstTransportStatuses": [
            200
          ],
          "hasUpstream503": false,
          "shortCircuitReason": "-",
          "isShortCircuit": false,
          "responseAction": "natural_answer",
          "businessIntent": "chat",
          "tonePosture": "advise",
          "expectedPosture": "advise",
          "expectedEvidenceType": "none",
          "isStrongDetailCase": false,
          "surfaceReply": "您应当迅速集中资源攻克医院 D 的产品 B 准入与上量，这是目前扭转达成率缺口的最快路径。\n\n从业务数据来看，产品 B 作为占据 34% 份额的核心品种，其 76% 的达成率严重拖累了大盘，而其关键阵地医院 D 的达成率更是低至 72%，直接导致 3 月份整体销售额环比增速从 2 月的 6.2% 骤降至 2.1%。目前的分析主要基于一季度累计的份额与达成缺口，由于缺乏 3 月份各医院具体的销量环比数据，尚无法精准判定医院 D 的进度滞后是受竞品干扰还是采购流程的短期波动。\n\n建议您在下周五前完成对医院 D 关键决策人的深度拜访，并确认是否需要我为您整理该医院近三个月的规格级进货趋势以辅助谈判？",
          "isNaturalCase": true,
          "isFailure": false
        },
        {
          "row": 20,
          "mode": "auto",
          "questionType": "advise",
          "http": 200,
          "errorCode": "-",
          "stage": "-",
          "upstreamStatus": "-",
          "durationMs": "-",
          "format": "structured",
          "attemptCount": "1",
          "repairApplied": "false",
          "requestId": "a555067b-622e-48bf-9f65-25e269c9c973",
          "waitFeeling": "中",
          "elapsedMs": 3387,
          "totalDurationMs": 2354,
          "contextChars": "1201",
          "finalStage": "first",
          "metaFormatReason": "structured_ok",
          "attemptDiagnostics": [
            {
              "stage": "first",
              "formatReason": "structured_ok",
              "qualityIssues": []
            }
          ],
          "firstTransportAttempts": "1",
          "firstTransportRetryApplied": "false",
          "firstTransportRetryRecovered": "false",
          "firstTransportStatuses": [
            200
          ],
          "hasUpstream503": false,
          "shortCircuitReason": "-",
          "isShortCircuit": false,
          "responseAction": "natural_answer",
          "businessIntent": "chat",
          "tonePosture": "advise",
          "expectedPosture": "advise",
          "expectedEvidenceType": "none",
          "isStrongDetailCase": false,
          "surfaceReply": "本周最有效的低成本策略是优先激活医院 K 的存量增长，以此作为填补达成率缺口的最快补充。\n\n虽然产品 B 在医院 D 的缺口最大，但医院 K 目前已实现 81% 的达成率，且其 11% 的份额贡献相对稳健，通过现有渠道进行小幅上量比攻克低达成率的硬骨头成本更低、见效更快。目前整体销售额环比增速已从 2 月的 6.2% 放缓至 3 月的 2.1%，在缺乏 3 月份各医院具体销量环比数据的情况下，稳住医院 K 这种中高达成率的阵地能有效防止大盘增速进一步下滑。\n\n建议您本周先与医院 K 的临床科室进行一次存量盘点，确认是否有未被满足的处方需求，您是否需要我为您调取该医院近期的规格级进货明细以寻找增量空间？",
          "isNaturalCase": true,
          "isFailure": false
        },
        {
          "row": 21,
          "mode": "auto",
          "questionType": "advise",
          "http": 200,
          "errorCode": "-",
          "stage": "-",
          "upstreamStatus": "-",
          "durationMs": "-",
          "format": "structured",
          "attemptCount": "1",
          "repairApplied": "false",
          "requestId": "c8f3c1e3-5ddd-4bb7-be1a-94e8eb7196d6",
          "waitFeeling": "中",
          "elapsedMs": 3061,
          "totalDurationMs": 2446,
          "contextChars": "1201",
          "finalStage": "first",
          "metaFormatReason": "structured_ok",
          "attemptDiagnostics": [
            {
              "stage": "first",
              "formatReason": "structured_ok",
              "qualityIssues": []
            }
          ],
          "firstTransportAttempts": "1",
          "firstTransportRetryApplied": "false",
          "firstTransportRetryRecovered": "false",
          "firstTransportStatuses": [
            200
          ],
          "hasUpstream503": false,
          "shortCircuitReason": "-",
          "isShortCircuit": false,
          "responseAction": "natural_answer",
          "businessIntent": "chat",
          "tonePosture": "advise",
          "expectedPosture": "advise",
          "expectedEvidenceType": "product_month",
          "isStrongDetailCase": true,
          "surfaceReply": "您应当重点盯防 2 月份的增长势头并优先复盘产品 B 的表现，以找回失去的增长动能。\n\n从数据来看，3 月份销售额环比仅增长 2.1%，较 2 月份 6.2% 的强劲回升明显放缓，而占据 34% 份额的核心产品 B 达成率仅为 76%，是拖累整体进度的主要因素。目前的分析主要受限于缺乏 3 月份各医院维度的具体销量环比数据，导致无法判定增速收窄是由于产品 B 在核心渠道的采购停滞，还是受其他竞品干扰。\n\n建议您本周优先对比产品 B 在 2 月与 3 月的进货明细，确认增长失速的具体环节，是否需要我为您导出该产品在各重点医院的月度波动对比表？",
          "isNaturalCase": true,
          "isFailure": false
        },
        {
          "row": 22,
          "mode": "auto",
          "questionType": "advise",
          "http": 200,
          "errorCode": "-",
          "stage": "-",
          "upstreamStatus": "-",
          "durationMs": "-",
          "format": "structured",
          "attemptCount": "1",
          "repairApplied": "false",
          "requestId": "91616868-350c-4751-aaf5-917c1a43a5eb",
          "waitFeeling": "快",
          "elapsedMs": 2851,
          "totalDurationMs": 2377,
          "contextChars": "1201",
          "finalStage": "first",
          "metaFormatReason": "structured_ok",
          "attemptDiagnostics": [
            {
              "stage": "first",
              "formatReason": "structured_ok",
              "qualityIssues": []
            }
          ],
          "firstTransportAttempts": "1",
          "firstTransportRetryApplied": "false",
          "firstTransportRetryRecovered": "false",
          "firstTransportStatuses": [
            200
          ],
          "hasUpstream503": false,
          "shortCircuitReason": "-",
          "isShortCircuit": false,
          "responseAction": "natural_answer",
          "businessIntent": "chat",
          "tonePosture": "judge",
          "expectedPosture": "advise",
          "expectedEvidenceType": "amount_quantity",
          "isStrongDetailCase": true,
          "surfaceReply": "您应当优先抓取“产品 B 的量价修复”与“医院 D 的进货提速”这两个核心杠杆。\n\n从业务数据看，产品 B 占据了 34% 的最高份额，但其达成率仅为 76%，且 3 月份整体销售额环比增速已从 2 月的 6.2% 明显收窄至 2.1%，修复这一核心品种的增长动能是提升大盘的关键；同时，医院 D 作为份额达 18% 的头号渠道，其 72% 的达成率远低于 88.1% 的平均水平，是目前金额与盒数双缺口最集中的阵地。目前的分析主要受限于缺乏 3 月份各医院维度的具体销量环比数据，尚无法判定医院 D 的进度滞后是受竞品干扰还是采购流程的短期波动。\n\n建议您下周优先针对医院 D 开展产品 B 的专项上量行动，您是否需要我为您对比该医院近两个月在金额与盒数上的具体波动差异？",
          "isNaturalCase": true,
          "isFailure": false
        },
        {
          "row": 23,
          "mode": "auto",
          "questionType": "advise",
          "http": 200,
          "errorCode": "-",
          "stage": "-",
          "upstreamStatus": "-",
          "durationMs": "-",
          "format": "structured",
          "attemptCount": "1",
          "repairApplied": "false",
          "requestId": "e4208184-7905-4b52-9702-808525b264ba",
          "waitFeeling": "中",
          "elapsedMs": 3177,
          "totalDurationMs": 2115,
          "contextChars": "1201",
          "finalStage": "first",
          "metaFormatReason": "structured_ok",
          "attemptDiagnostics": [
            {
              "stage": "first",
              "formatReason": "structured_ok",
              "qualityIssues": []
            }
          ],
          "firstTransportAttempts": "1",
          "firstTransportRetryApplied": "false",
          "firstTransportRetryRecovered": "false",
          "firstTransportStatuses": [
            200
          ],
          "hasUpstream503": false,
          "shortCircuitReason": "-",
          "isShortCircuit": false,
          "responseAction": "natural_answer",
          "businessIntent": "chat",
          "tonePosture": "judge",
          "expectedPosture": "advise",
          "expectedEvidenceType": "quantity",
          "isStrongDetailCase": true,
          "surfaceReply": "您应当立即启动对产品 B 在医院 D 的专项补货计划，这是实现盒数环比 5% 增长的最直接突破口。\n\n依据在于产品 B 虽占据 34% 的最高份额，但目前达成率仅为 76%，且 3 月份整体销售额环比增速已从 2 月的 6.2% 骤降至 2.1%，通过修复核心品种在份额最大的医院 D（达成率仅 72%）的进货节奏，能最快释放盒数增量。目前的分析边界在于缺乏 3 月份各医院维度的具体销量环比数据，尚无法判定医院 D 的盒数缺口是由于库存积压还是终端处方量萎缩。\n\n建议您本周先核实医院 D 的药房库存水位，确认是否具备立即补货的条件，需要我为您调取该医院产品 B 近三个月的进货盒数趋势吗？",
          "isNaturalCase": true,
          "isFailure": false
        },
        {
          "row": 24,
          "mode": "auto",
          "questionType": "advise",
          "http": 200,
          "errorCode": "-",
          "stage": "-",
          "upstreamStatus": "-",
          "durationMs": "-",
          "format": "structured",
          "attemptCount": "1",
          "repairApplied": "false",
          "requestId": "8abebb72-4e17-473a-81a6-b409e2220ca4",
          "waitFeeling": "中",
          "elapsedMs": 3353,
          "totalDurationMs": 2380,
          "contextChars": "1201",
          "finalStage": "first",
          "metaFormatReason": "structured_ok",
          "attemptDiagnostics": [
            {
              "stage": "first",
              "formatReason": "structured_ok",
              "qualityIssues": []
            }
          ],
          "firstTransportAttempts": "1",
          "firstTransportRetryApplied": "false",
          "firstTransportRetryRecovered": "false",
          "firstTransportStatuses": [
            200
          ],
          "hasUpstream503": false,
          "shortCircuitReason": "-",
          "isShortCircuit": false,
          "responseAction": "natural_answer",
          "businessIntent": "chat",
          "tonePosture": "advise",
          "expectedPosture": "advise",
          "expectedEvidenceType": "month",
          "isStrongDetailCase": true,
          "surfaceReply": "建议您将本月的工作重心放在“止跌回稳”上，优先解决 3 月份增速大幅放缓的问题，其次再复盘 2 月份的增长经验。\n\n从趋势看，3 月份销售额环比增速已从 2 月份的 6.2% 骤降至 2.1%，增长动能明显衰减，而核心产品 B 仅 76% 的达成率是拖累大盘的主因。目前由于缺乏 3 月份各医院维度的具体销量环比数据，无法判定这种失速是由于医院 D 等核心渠道的采购周期性波动，还是终端处方量出现了结构性下滑。\n\n建议您本周优先排查产品 B 在 3 月份的进货断档情况，您是否需要我为您对比 2 月与 3 月各重点医院的进货波动差值，以锁定具体的流失环节？",
          "isNaturalCase": true,
          "isFailure": false
        }
      ]
    }
  ]
}